aiopolly/__init__.py
aiopolly/encoder.py
aiopolly/polly/__init__.py
aiopolly/polly/api.py
aiopolly/polly/config.py
aiopolly/polly/polly.py
aiopolly/types/__init__.py
aiopolly/types/base.py
aiopolly/types/lexicon.py
aiopolly/types/method.py
aiopolly/types/params.py
aiopolly/types/speech.py
aiopolly/types/synthesis_task.py
aiopolly/types/voice.py
aiopolly/utils/__init__.py
aiopolly/utils/case.py
aiopolly/utils/credentials.py
aiopolly/utils/errors_parser.py
aiopolly/utils/exceptions.py
aiopolly/utils/json.py
aiopolly/utils/lexicon.py
aiopolly/utils/mixins.py
aiopolly/utils/payload.py
aiopolly/utils/strenum.py
aiopolly/utils/converter/__init__.py
aiopolly/utils/converter/base.py
aiopolly/utils/converter/opus_converter.py
aiopolly/utils/ssml/__init__.py
aiopolly/utils/ssml/actions.py
aiopolly/utils/ssml/params.py
aiopolly-0.2.2.dist-info/METADATA
aiopolly-0.2.2.dist-info/WHEEL
aiopolly-0.2.2.dist-info/top_level.txt
aiopolly-0.2.2.dist-info/RECORD
