Metadata-Version: 2.1
Name: aiopolly
Version: 0.2.2
Summary: Asynchronous wrapper for AWS Polly API
Home-page: https://github.com/MrMrRobat/aiopolly
Author: MrMrRobat
Author-email: appkiller16@gmail.com
License: MIT
Platform: UNKNOWN
Classifier: Development Status :: 4 - Beta
Classifier: Environment :: Console
Classifier: Framework :: AsyncIO
Classifier: Intended Audience :: Developers
Classifier: Intended Audience :: System Administrators
Classifier: License :: OSI Approved :: MIT License
Classifier: Programming Language :: Python :: 3.7
Classifier: Programming Language :: Python :: 3.8
Classifier: Topic :: Software Development :: Libraries :: Application Frameworks
Requires-Dist: aiofiles (==0.4.0)
Requires-Dist: aiohttp (>=3.5.4)
Requires-Dist: botocore (>=1.12.0)
Requires-Dist: certifi (>=2019.3.9)
Requires-Dist: pydantic (>=0.27)
